sclive/__init__.py
sclive/dataio/__init__.py
sclive/dataio/get_dimred_with_exprs_func.py
sclive/dataio/get_dimred_with_metas_func.py
sclive/dataio/get_gene_exprs_func.py
sclive/dataio/get_metas_func.py
sclive/live_dash/__init__.py
sclive/live_dash/_live_dash_server.py
sclive/live_dash/_live_dash_ui.py
sclive/live_dash/live_dash.py
sclive/live_dash/live_dash_app.py
sclive/plotting/__init__.py
sclive/plotting/_layout_funcs.py
sclive/plotting/box_plt_func.py
sclive/plotting/dimred_coexprs_2d_func.py
sclive/plotting/dimred_coexprs_3d_func.py
sclive/plotting/dimred_plt_2d_func.py
sclive/plotting/dimred_plt_3d_func.py
sclive/plotting/dot_plt_func.py
sclive/plotting/heatmap_plt_func.py
sclive/plotting/prop_plt_func.py
sclive/plotting/violin_plt_func.py
sclive-0.3.0.dist-info/LICENSE
sclive-0.3.0.dist-info/METADATA
sclive-0.3.0.dist-info/WHEEL
sclive-0.3.0.dist-info/RECORD
