Metadata-Version: 2.3
Name: sclive
Version: 0.3.0
Summary: Single cell analysis plotting function with interactive and web development friendly outputs.
License: LICENSE
Author: Adnan Cihan Cakar
Author-email: cakar.adnancihan@gmail.com
Requires-Python: >=3.11,<4.0
Classifier: License :: Other/Proprietary License
Classifier: Programming Language :: Python :: 3
Classifier: Programming Language :: Python :: 3.11
Classifier: Programming Language :: Python :: 3.12
Classifier: Programming Language :: Python :: 3.13
Requires-Dist: anndata (>=0.11.1,<0.12.0)
Requires-Dist: distinctipy (>=1.3.4,<2.0.0)
Requires-Dist: plotly (>=5.24.1,<6.0.0)
Requires-Dist: polars[pandas,pyarrow] (>=1.18.0,<2.0.0)
Requires-Dist: shinywidgets (>=0.5.2,<0.6.0)
